mlir_pygments/__init__.py
mlir_pygments/mlir.py
mlir_pygments/py.typed
mlir_pygments-1.0.0.dist-info/licenses/LICENSE.md
mlir_pygments-1.0.0.dist-info/WHEEL
mlir_pygments-1.0.0.dist-info/entry_points.txt
mlir_pygments-1.0.0.dist-info/METADATA
mlir_pygments-1.0.0.dist-info/RECORD
