Metadata-Version: 2.4
Name: mlir-pygments
Version: 1.0.0
Summary: Pygments lexer for MLIR
Author: Lukas Burgholzer
Author-email: Lukas Burgholzer <burgholzer@me.com>
License-Expression: MIT
License-File: LICENSE.md
Classifier: Development Status :: 5 - Production/Stable
Classifier: Intended Audience :: Science/Research
Classifier: Natural Language :: English
Classifier: Operating System :: MacOS
Classifier: Operating System :: Microsoft :: Windows
Classifier: Operating System :: POSIX :: Linux
Classifier: Programming Language :: C++
Classifier: Programming Language :: Python
Classifier: Programming Language :: Python :: 3 :: Only
Classifier: Typing :: Typed
Requires-Dist: pygments>=2.0
Requires-Python: >=3.10
